cfresolve/__init__.py
cfresolve/__main__.py
cfresolve/_version.py
cfresolve/cli.py
cfresolve/exceptions.py
cfresolve-0.0.2.dist-info/METADATA
cfresolve-0.0.2.dist-info/WHEEL
cfresolve-0.0.2.dist-info/entry_points.txt
cfresolve-0.0.2.dist-info/top_level.txt
cfresolve-0.0.2.dist-info/RECORD
