Metadata-Version: 2.1
Name: cfresolve
Version: 0.0.2
Summary: Pings domains that use cloudflare to retrieve edge ips
Author-email: tempookian <tempookian@gmail.com>
Project-URL: Homepage, https://github.com/tempookian/cfresolve/
Project-URL: Bug Tracker, https://github.com/tempookian/cfresolve/issues
Classifier: Programming Language :: Python :: 3
Classifier: License :: OSI Approved :: GNU General Public License v3 (GPLv3)
Classifier: Operating System :: OS Independent
Requires-Python: >=3.8
Requires-Dist: polars ==0.20.30
Requires-Dist: rich-click ==1.8.2
Requires-Dist: pydantic ==2.7.2
Requires-Dist: validators ==0.28.3
Requires-Dist: requests ==2.32.2
